{
	"$schema": "https://json-schema.org/draft/2020-12/schema",
	"description": "JSON Schema generated by XMLSpy v2025 (x64) (https://www.altova.com)",
	"type": "object",
	"properties": {
		"@xmlns:env": {
			"default": "urn:un:unece:uncefact:data:standard:Envelope"
		},
		"@xmlns:hza": {
			"default": "urn:un:unece:uncefact:data:standard:HZA:MMTPlus"
		},
		"@xmlns:mai": {
			"default": "urn:un:unece:uncefact:data:standard:MAI:MMTPlus"
		},
		"@xmlns:qdt": {
			"default": "urn:un:unece:uncefact:data:standard:QualifiedDataType:100"
		},
		"@xmlns:ram": {
			"default": "urn:un:unece:uncefact:data:standard:ReusableAggregateBusinessInformationEntity:100"
		},
		"@xmlns:udt": {
			"default": "urn:un:unece:uncefact:data:standard:UnqualifiedDataType:100"
		},
		"env:Envelope": {
			"$ref": "#/$defs/.env:Envelope"
		}
	},
	"additionalProperties": false,
	"$defs": {
		".env:Envelope": {
			"type": "object",
			"properties": {
				"hza:HZA": {
					"$ref": "#/$defs/.hza:HZA"
				},
				"mai:MAI": {
					"$ref": "#/$defs/.mai:MAI"
				}
			},
			"required": [
				"mai:MAI"
			],
			"additionalProperties": false
		},
		".hza:HZA": {
			"$ref": "#/$defs/hza:HZAType_2"
		},
		".mai:MAI": {
			"$ref": "#/$defs/mai:MAIType_2"
		},
		"hza:HZAType_2": {
			"description": "HZA- Notification of hazardous materials (dangerous and polluting goods) on board at arrival\nMA\nBSP Master. Details",
			"type": "object",
			"properties": {
				"hza:ExchangedDeclaration": {
					"$ref": "#/$defs/ram:ExchangedDeclarationType_2"
				},
				"hza:ExchangedDocument": {
					"$ref": "#/$defs/ram:ExchangedDocumentType_2"
				},
				"hza:SpecifiedLogisticsTransportEquipment": {
					"type": "array",
					"items": {
						"$ref": "#/$defs/ram:LogisticsTransportEquipmentType_2"
					}
				},
				"hza:SpecifiedLogisticsTransportMovement": {
					"$ref": "#/$defs/ram:LogisticsTransportMovementType_2"
				},
				"hza:SpecifiedSupplyChainConsignment": {
					"type": "array",
					"minItems": 1,
					"items": {
						"$ref": "#/$defs/ram:SupplyChainConsignmentType_2"
					}
				}
			},
			"required": [
				"hza:SpecifiedLogisticsTransportMovement",
				"hza:SpecifiedSupplyChainConsignment"
			],
			"additionalProperties": false
		},
		"mai:MAIType_2": {
			"description": "MAI - Main message header\nMA\nBSP Master. Details",
			"type": "object",
			"properties": {
				"mai:ExchangedDeclaration": {
					"$ref": "#/$defs/ram:ExchangedDeclarationType_3"
				},
				"mai:ExchangedDocument": {
					"$ref": "#/$defs/ram:ExchangedDocumentType_3"
				},
				"mai:SpecifiedLogisticsTransportMovement": {
					"$ref": "#/$defs/ram:LogisticsTransportMovementType_4"
				}
			},
			"required": [
				"mai:ExchangedDeclaration",
				"mai:ExchangedDocument"
			],
			"additionalProperties": false
		},
		"qdt:AttachmentTypeCodeContentType_2": {
			"type": "string",
			"maxLength": 17,
			"enum": [
				"ATT-002",
				"ATT-004",
				"ATT-009",
				"ATT-011",
				"ATT-015",
				"ATT-016",
				"ATT-017",
				"ATT-022",
				"ATT-024",
				"ATT-025",
				"ATT-026",
				"ATT-027",
				"ATT-028",
				"ATT-034",
				"ATT-035",
				"ATT-036",
				"ATT-039",
				"ATT-040",
				"ATT-041",
				"ATT-046",
				"ATT-052",
				"ATT-054",
				"ATT-055",
				"ATT-056",
				"ATT-057",
				"ATT-059",
				"ATT-060"
			]
		},
		"qdt:AttachmentTypeCodeType_2": {
			"description": "QDT\nAttachment Type_ Code. Type",
			"$ref": "#/$defs/qdt:AttachmentTypeCodeContentType_2",
			"additionalProperties": false
		},
		"qdt:CargoOperationCodeContentType_2": {
			"type": "string",
			"maxLength": 17,
			"enum": [
				"COP-03",
				"COP-04",
				"COP-05",
				"COP-06",
				"COP-08"
			]
		},
		"qdt:CargoOperationCodeType_2": {
			"description": "QDT\nCargo Operation_ Code. Type",
			"$ref": "#/$defs/qdt:CargoOperationCodeContentType_2",
			"additionalProperties": false
		},
		"qdt:ClassCategoryCodeContentType_2": {
			"type": "string",
			"maxLength": 3,
			"enum": [
				"1",
				"2",
				"3"
			]
		},
		"qdt:ClassCategoryCodeType_2": {
			"description": "QDT\nClass 7 Category_ Code. Type",
			"$ref": "#/$defs/qdt:ClassCategoryCodeContentType_2",
			"additionalProperties": false
		},
		"qdt:CountryIDType_2": {
			"description": "QDT\nCountry_ Identifier. Type",
			"type": "string",
			"minLength": 2,
			"maxLength": 2,
			"enum": [
				"AD",
				"AE",
				"AF",
				"AG",
				"AI",
				"AL",
				"AM",
				"AO",
				"AQ",
				"AR",
				"AS",
				"AT",
				"AU",
				"AW",
				"AX",
				"AZ",
				"BA",
				"BB",
				"BD",
				"BE",
				"BF",
				"BG",
				"BH",
				"BI",
				"BJ",
				"BL",
				"BM",
				"BN",
				"BO",
				"BQ",
				"BR",
				"BS",
				"BT",
				"BV",
				"BW",
				"BY",
				"BZ",
				"CA",
				"CC",
				"CD",
				"CF",
				"CG",
				"CH",
				"CI",
				"CK",
				"CL",
				"CM",
				"CN",
				"CO",
				"CR",
				"CU",
				"CV",
				"CW",
				"CX",
				"CY",
				"CZ",
				"DE",
				"DJ",
				"DK",
				"DM",
				"DO",
				"DZ",
				"EC",
				"EE",
				"EG",
				"EH",
				"ER",
				"ES",
				"ET",
				"FI",
				"FJ",
				"FK",
				"FM",
				"FO",
				"FR",
				"GA",
				"GB",
				"GD",
				"GE",
				"GF",
				"GG",
				"GH",
				"GI",
				"GL",
				"GM",
				"GN",
				"GP",
				"GQ",
				"GR",
				"GS",
				"GT",
				"GU",
				"GW",
				"GY",
				"HK",
				"HM",
				"HN",
				"HR",
				"HT",
				"HU",
				"ID",
				"IE",
				"IL",
				"IM",
				"IN",
				"IO",
				"IQ",
				"IR",
				"IS",
				"IT",
				"JE",
				"JM",
				"JO",
				"JP",
				"KE",
				"KG",
				"KH",
				"KI",
				"KM",
				"KN",
				"KP",
				"KR",
				"KW",
				"KY",
				"KZ",
				"LA",
				"LB",
				"LC",
				"LI",
				"LK",
				"LR",
				"LS",
				"LT",
				"LU",
				"LV",
				"LY",
				"MA",
				"MC",
				"MD",
				"ME",
				"MF",
				"MG",
				"MH",
				"MK",
				"ML",
				"MM",
				"MN",
				"MO",
				"MP",
				"MQ",
				"MR",
				"MS",
				"MT",
				"MU",
				"MV",
				"MW",
				"MX",
				"MY",
				"MZ",
				"NA",
				"NC",
				"NE",
				"NF",
				"NG",
				"NI",
				"NL",
				"NO",
				"NP",
				"NR",
				"NU",
				"NZ",
				"OM",
				"PA",
				"PE",
				"PF",
				"PG",
				"PH",
				"PK",
				"PL",
				"PM",
				"PN",
				"PR",
				"PS",
				"PT",
				"PW",
				"PY",
				"QA",
				"RE",
				"RO",
				"RS",
				"RU",
				"RW",
				"SA",
				"SB",
				"SC",
				"SD",
				"SE",
				"SG",
				"SH",
				"SI",
				"SJ",
				"SK",
				"SL",
				"SM",
				"SN",
				"SO",
				"SR",
				"SS",
				"ST",
				"SV",
				"SX",
				"SY",
				"SZ",
				"TC",
				"TD",
				"TF",
				"TG",
				"TH",
				"TJ",
				"TK",
				"TL",
				"TM",
				"TN",
				"TO",
				"TR",
				"TT",
				"TV",
				"TW",
				"TZ",
				"UA",
				"UG",
				"UM",
				"US",
				"UY",
				"UZ",
				"VA",
				"VC",
				"VE",
				"VG",
				"VI",
				"VN",
				"VU",
				"WF",
				"WS",
				"YE",
				"YT",
				"ZA",
				"ZM",
				"ZW"
			]
		},
		"qdt:DangerousGoodsRegulationCodeContentType_2": {
			"type": "string",
			"maxLength": 3,
			"enum": [
				"ADY",
				"ADZ",
				"AEA",
				"AEB",
				"IMD"
			]
		},
		"qdt:DangerousGoodsRegulationCodeContentType_3": {
			"type": "string",
			"maxLength": 3,
			"enum": [
				"ADR",
				"ADS",
				"ADT",
				"ADU",
				"ADV",
				"ADW",
				"ADX",
				"ADY",
				"ADZ",
				"AEA",
				"AEB",
				"AGS",
				"ANR",
				"ARD",
				"CFR",
				"COM",
				"GVE",
				"GVS",
				"ICA",
				"IMD",
				"RGE",
				"RID",
				"UI",
				"ZZZ"
			]
		},
		"qdt:DangerousGoodsRegulationCodeType_2": {
			"description": "QDT\nDangerous Goods Regulation_ Code. Type",
			"$ref": "#/$defs/qdt:DangerousGoodsRegulationCodeContentType_2",
			"additionalProperties": false
		},
		"qdt:DangerousGoodsRegulationCodeType_3": {
			"description": "QDT\nDangerous Goods Regulation_ Code. Type",
			"$ref": "#/$defs/qdt:DangerousGoodsRegulationCodeContentType_3",
			"additionalProperties": false
		},
		"qdt:FlashpointDescriptionCodeContentType_2": {
			"type": "string",
			"maxLength": 8,
			"enum": [
				"GT60CEL",
				"LE60CEL",
				"NF",
				"SF"
			]
		},
		"qdt:FlashpointDescriptionCodeType_2": {
			"description": "QDT\nFlashpoint Description_ Code. Type",
			"$ref": "#/$defs/qdt:FlashpointDescriptionCodeContentType_2",
			"additionalProperties": false
		},
		"qdt:FormalityTypesCodeContentType_2": {
			"type": "string",
			"maxLength": 3,
			"enum": [
				"HZA"
			]
		},
		"qdt:FormalityTypesCodeType_2": {
			"description": "QDT\nFormality Types_ Code. Type",
			"$ref": "#/$defs/qdt:FormalityTypesCodeContentType_2",
			"additionalProperties": false
		},
		"qdt:FormattedDateTimeType": {
			"type": "string",
			"format": "date-time"
		},
		"qdt:FormattedDateType": {
			"type": "string",
			"format": "date"
		},
		"qdt:IMDGDangerousGoodsPackingGroupCodeContentType_2": {
			"type": "string",
			"maxLength": 3,
			"enum": [
				"I",
				"II",
				"III"
			]
		},
		"qdt:IMDGDangerousGoodsPackingGroupCodeType_2": {
			"description": "QDT\nIMDG_Dangerous Goods Packing Group_ Code. Type",
			"$ref": "#/$defs/qdt:IMDGDangerousGoodsPackingGroupCodeContentType_2",
			"additionalProperties": false
		},
		"qdt:INFShipClassIDType_2": {
			"description": "QDT\nINF Ship Class_ Identifier. Type",
			"type": "string",
			"minLength": 4,
			"maxLength": 4,
			"enum": [
				"INF1",
				"INF2",
				"INF3"
			]
		},
		"qdt:MIMECodeType_2": {
			"description": "QDT\nMIME_ Code. Type",
			"$ref": "#/$defs/qdt:token",
			"additionalProperties": false
		},
		"qdt:MarkingInstructionCodeContentType_2": {
			"type": "string",
			"maxLength": 3,
			"enum": [
				"1",
				"2",
				"3",
				"4",
				"5",
				"6",
				"7",
				"8",
				"9",
				"10",
				"11",
				"12",
				"13",
				"14",
				"15",
				"16",
				"17",
				"18",
				"19",
				"20",
				"21",
				"22",
				"23",
				"24",
				"25",
				"26",
				"27",
				"28",
				"29",
				"30",
				"31",
				"32",
				"33",
				"34",
				"35",
				"36",
				"37",
				"38",
				"39",
				"40",
				"41",
				"42",
				"43",
				"44",
				"45",
				"46",
				"47",
				"48",
				"49",
				"ZZZ"
			]
		},
		"qdt:MarkingInstructionCodeType_2": {
			"description": "QDT\nMarking Instruction_ Code. Type",
			"$ref": "#/$defs/qdt:MarkingInstructionCodeContentType_2",
			"additionalProperties": false
		},
		"qdt:MessageFunctionCodeContentType_2": {
			"type": "string",
			"maxLength": 3,
			"enum": [
				"1",
				"9"
			]
		},
		"qdt:MessageFunctionCodeType_2": {
			"description": "QDT\nMessage Function_ Code. Type",
			"$ref": "#/$defs/qdt:MessageFunctionCodeContentType_2",
			"additionalProperties": false
		},
		"qdt:PackageTypeCodeContentType_2": {
			"type": "string",
			"maxLength": 2,
			"enum": [
				"43",
				"44",
				"1A",
				"1B",
				"1D",
				"1F",
				"1G",
				"1W",
				"2C",
				"3A",
				"3H",
				"4A",
				"4B",
				"4C",
				"4D",
				"4F",
				"4G",
				"4H",
				"5H",
				"5L",
				"5M",
				"6H",
				"6P",
				"7A",
				"7B",
				"8A",
				"8B",
				"8C",
				"AA",
				"AB",
				"AC",
				"AD",
				"AE",
				"AF",
				"AG",
				"AH",
				"AI",
				"AJ",
				"AL",
				"AM",
				"AP",
				"AT",
				"AV",
				"B4",
				"BA",
				"BB",
				"BC",
				"BD",
				"BE",
				"BF",
				"BG",
				"BH",
				"BI",
				"BJ",
				"BK",
				"BL",
				"BM",
				"BN",
				"BO",
				"BP",
				"BQ",
				"BR",
				"BS",
				"BT",
				"BU",
				"BV",
				"BW",
				"BX",
				"BY",
				"BZ",
				"CA",
				"CB",
				"CC",
				"CD",
				"CE",
				"CF",
				"CG",
				"CH",
				"CI",
				"CJ",
				"CK",
				"CL",
				"CM",
				"CN",
				"CO",
				"CP",
				"CQ",
				"CR",
				"CS",
				"CT",
				"CU",
				"CV",
				"CW",
				"CX",
				"CY",
				"CZ",
				"DA",
				"DB",
				"DC",
				"DG",
				"DH",
				"DI",
				"DJ",
				"DK",
				"DL",
				"DM",
				"DN",
				"DP",
				"DR",
				"DS",
				"DT",
				"DU",
				"DV",
				"DW",
				"DX",
				"DY",
				"EC",
				"ED",
				"EE",
				"EF",
				"EG",
				"EH",
				"EI",
				"EN",
				"FB",
				"FC",
				"FD",
				"FE",
				"FI",
				"FL",
				"FO",
				"FP",
				"FR",
				"FT",
				"FW",
				"FX",
				"GB",
				"GI",
				"GL",
				"GR",
				"GU",
				"GY",
				"GZ",
				"HA",
				"HB",
				"HC",
				"HG",
				"HN",
				"HR",
				"IA",
				"IB",
				"IC",
				"ID",
				"IE",
				"IF",
				"IG",
				"IH",
				"IK",
				"IL",
				"IN",
				"IZ",
				"JB",
				"JC",
				"JG",
				"JR",
				"JT",
				"JY",
				"KG",
				"KI",
				"LE",
				"LG",
				"LT",
				"LU",
				"LV",
				"LZ",
				"MA",
				"MB",
				"MC",
				"ME",
				"MR",
				"MS",
				"MT",
				"MW",
				"MX",
				"NA",
				"NE",
				"NF",
				"NG",
				"NS",
				"NT",
				"NU",
				"NV",
				"O1",
				"O2",
				"O3",
				"O4",
				"O5",
				"O6",
				"O7",
				"O8",
				"O9",
				"OA",
				"OB",
				"OC",
				"OD",
				"OE",
				"OF",
				"OG",
				"OH",
				"OI",
				"OJ",
				"OK",
				"OL",
				"OM",
				"ON",
				"OP",
				"OQ",
				"OR",
				"OS",
				"OT",
				"OU",
				"OV",
				"OW",
				"OX",
				"OY",
				"OZ",
				"P1",
				"P2",
				"P3",
				"P4",
				"PA",
				"PB",
				"PC",
				"PD",
				"PE",
				"PF",
				"PG",
				"PH",
				"PI",
				"PJ",
				"PK",
				"PL",
				"PN",
				"PO",
				"PP",
				"PR",
				"PT",
				"PU",
				"PV",
				"PX",
				"PY",
				"PZ",
				"QA",
				"QB",
				"QC",
				"QD",
				"QF",
				"QG",
				"QH",
				"QJ",
				"QK",
				"QL",
				"QM",
				"QN",
				"QP",
				"QQ",
				"QR",
				"QS",
				"RD",
				"RG",
				"RJ",
				"RK",
				"RL",
				"RO",
				"RT",
				"RZ",
				"SA",
				"SB",
				"SC",
				"SD",
				"SE",
				"SH",
				"SI",
				"SK",
				"SL",
				"SM",
				"SO",
				"SP",
				"SS",
				"ST",
				"SU",
				"SV",
				"SW",
				"SY",
				"SZ",
				"T1",
				"TB",
				"TC",
				"TD",
				"TE",
				"TG",
				"TI",
				"TK",
				"TL",
				"TN",
				"TO",
				"TR",
				"TS",
				"TT",
				"TU",
				"TV",
				"TW",
				"TY",
				"TZ",
				"UC",
				"UN",
				"VA",
				"VG",
				"VI",
				"VK",
				"VL",
				"VN",
				"VO",
				"VP",
				"VQ",
				"VR",
				"VS",
				"VY",
				"WA",
				"WB",
				"WC",
				"WD",
				"WF",
				"WG",
				"WH",
				"WJ",
				"WK",
				"WL",
				"WM",
				"WN",
				"WP",
				"WQ",
				"WR",
				"WS",
				"WT",
				"WU",
				"WV",
				"WW",
				"WX",
				"WY",
				"WZ",
				"XA",
				"XB",
				"XC",
				"XD",
				"XF",
				"XG",
				"XH",
				"XJ",
				"XK",
				"YA",
				"YB",
				"YC",
				"YD",
				"YF",
				"YG",
				"YH",
				"YJ",
				"YK",
				"YL",
				"YM",
				"YN",
				"YP",
				"YQ",
				"YR",
				"YS",
				"YT",
				"YV",
				"YW",
				"YX",
				"YY",
				"YZ",
				"ZA",
				"ZB",
				"ZC",
				"ZD",
				"ZF",
				"ZG",
				"ZH",
				"ZJ",
				"ZK",
				"ZL",
				"ZM",
				"ZN",
				"ZP",
				"ZQ",
				"ZR",
				"ZS",
				"ZT",
				"ZU",
				"ZV",
				"ZW",
				"ZX",
				"ZY",
				"ZZ"
			]
		},
		"qdt:PackageTypeCodeType_2": {
			"description": "QDT\nPackage Type_ Code. Type",
			"$ref": "#/$defs/qdt:PackageTypeCodeContentType_2",
			"additionalProperties": false
		},
		"qdt:PackagingLevelCodeContentType_2": {
			"type": "string",
			"maxLength": 3,
			"enum": [
				"1",
				"3"
			]
		},
		"qdt:PackagingLevelCodeType_2": {
			"description": "QDT\nPackaging Level_ Code. Type",
			"$ref": "#/$defs/qdt:PackagingLevelCodeContentType_2",
			"additionalProperties": false
		},
		"qdt:PartyRoleCodeContentType_2": {
			"type": "string",
			"maxLength": 3,
			"enum": [
				"AG",
				"CA",
				"CPE",
				"POA"
			]
		},
		"qdt:PartyRoleCodeType_2": {
			"description": "QDT\nParty Role_ Code. Type",
			"$ref": "#/$defs/qdt:PartyRoleCodeContentType_2",
			"additionalProperties": false
		},
		"qdt:StatementTypeCodeContentType_2": {
			"type": "string",
			"maxLength": 8,
			"enum": [
				"ST-FI-01",
				"ST-FI-02",
				"ST-IT-01",
				"ST-IT-02",
				"ST-IT-03",
				"ST-IT-04",
				"ST-IT-05",
				"ST-IT-06",
				"ST-IT-07",
				"ST-IT-08",
				"ST-IT-09",
				"ST-IT-10",
				"ST-IT-11",
				"ST-IT-12",
				"ST-IT-13",
				"ST-IT-14",
				"ST-IT-15",
				"ST-IT-16",
				"ST-IT-17"
			]
		},
		"qdt:StatementTypeCodeType_2": {
			"description": "QDT\nStatement Type_ Code. Type",
			"$ref": "#/$defs/qdt:StatementTypeCodeContentType_2",
			"additionalProperties": false
		},
		"qdt:TankStatusCodeContentType_2": {
			"type": "string",
			"maxLength": 17,
			"enum": [
				"TEC",
				"TECI",
				"TEU",
				"TEUI",
				"TNE",
				"TNEI",
				"TR",
				"TRI"
			]
		},
		"qdt:TankStatusCodeType_2": {
			"description": "QDT\nTank Status_ Code. Type",
			"$ref": "#/$defs/qdt:TankStatusCodeContentType_2",
			"additionalProperties": false
		},
		"qdt:TemperatureUnitMeasureType_2": {
			"description": "QDT\nTemperature_ Unit_ Measure. Type",
			"type": [
				"object"
			],
			"properties": {
				"$": {
					"$ref": "#/$defs/qdt:decimal_4"
				},
				"@unitCode": {
					"$ref": "#/$defs/qdt:TemperatureUnitMeasureUnitCodeContentType"
				}
			},
			"required": [
				"@unitCode"
			],
			"additionalProperties": false
		},
		"qdt:TemperatureUnitMeasureType_3": {
			"description": "QDT\nTemperature_ Unit_ Measure. Type",
			"oneOf": [
				{
					"type": "object",
					"properties": {
						"$": {
							"$ref": "#/$defs/qdt:decimal_4"
						},
						"@unitCode": {
							"$ref": "#/$defs/qdt:TemperatureUnitMeasureUnitCodeContentType"
						}
					},
					"additionalProperties": false
				},
				{
					"$ref": "#/$defs/qdt:decimal_4"
				}
			]
		},
		"qdt:TemperatureUnitMeasureUnitCodeContentType": {
			"type": "string",
			"minLength": 1,
			"maxLength": 4,
			"enum": [
				"CEL"
			]
		},
		"qdt:TransportEquipmentOperationalStatusCodeContentType_2": {
			"type": "string",
			"maxLength": 3,
			"enum": [
				"4",
				"5",
				"10",
				"11",
				"12",
				"13",
				"14",
				"15",
				"16",
				"17",
				"18",
				"19",
				"20",
				"21",
				"22",
				"23",
				"24",
				"25",
				"26",
				"27",
				"28",
				"29",
				"30",
				"31",
				"32"
			]
		},
		"qdt:TransportEquipmentOperationalStatusCodeType_2": {
			"description": "QDT\nTransport Equipment Operational Status_ Code. Type",
			"$ref": "#/$defs/qdt:TransportEquipmentOperationalStatusCodeContentType_2",
			"additionalProperties": false
		},
		"qdt:TransportEquipmentSizeTypeCodeContentType_2": {
			"type": "string",
			"maxLength": 10,
			"enum": [
				"1",
				"2",
				"6",
				"7",
				"9",
				"10",
				"12",
				"13",
				"14",
				"15",
				"16",
				"17",
				"18",
				"19",
				"20",
				"21",
				"22",
				"23",
				"24",
				"25",
				"26",
				"27",
				"28",
				"29",
				"30",
				"31",
				"32",
				"33",
				"34",
				"35",
				"36",
				"37",
				"38",
				"39",
				"40",
				"41",
				"42",
				"43",
				"44",
				"45",
				"46",
				"47"
			]
		},
		"qdt:TransportEquipmentSizeTypeCodeListAgencyIDContentType": {
			"type": "string",
			"enum": [
				"6"
			]
		},
		"qdt:TransportEquipmentSizeTypeCodeType_2": {
			"description": "QDT\nTransport Equipment Size Type_ Code. Type",
			"type": [
				"object"
			],
			"properties": {
				"$": {
					"$ref": "#/$defs/qdt:TransportEquipmentSizeTypeCodeContentType_2"
				},
				"@listAgencyID": {
					"$ref": "#/$defs/qdt:TransportEquipmentSizeTypeCodeListAgencyIDContentType"
				}
			},
			"required": [
				"@listAgencyID"
			],
			"additionalProperties": false
		},
		"qdt:TransportModeCodeContentType_2": {
			"type": "string",
			"maxLength": 17,
			"enum": [
				"0",
				"1",
				"2",
				"3",
				"4",
				"5",
				"6",
				"7",
				"8",
				"9"
			]
		},
		"qdt:TransportModeCodeType_2": {
			"description": "QDT\nTransport Mode_ Code. Type",
			"$ref": "#/$defs/qdt:TransportModeCodeContentType_2",
			"additionalProperties": false
		},
		"qdt:UnitMeasureType_2": {
			"description": "QDT\nUnit_ Measure. Type",
			"oneOf": [
				{
					"type": "object",
					"properties": {
						"$": {
							"$ref": "#/$defs/qdt:decimal_2"
						},
						"@unitCode": {
							"$ref": "#/$defs/qdt:UnitMeasureUnitCodeContentType_2"
						}
					},
					"additionalProperties": false
				},
				{
					"$ref": "#/$defs/qdt:decimal_2"
				}
			]
		},
		"qdt:UnitMeasureType_3": {
			"description": "QDT\nUnit_ Measure. Type",
			"type": [
				"object"
			],
			"properties": {
				"$": {
					"$ref": "#/$defs/qdt:decimal_3"
				},
				"@unitCode": {
					"$ref": "#/$defs/qdt:UnitMeasureUnitCodeContentType_3"
				}
			},
			"required": [
				"@unitCode"
			],
			"additionalProperties": false
		},
		"qdt:UnitMeasureType_4": {
			"description": "QDT\nUnit_ Measure. Type",
			"type": [
				"object"
			],
			"properties": {
				"$": {
					"$ref": "#/$defs/qdt:decimal_4"
				},
				"@unitCode": {
					"$ref": "#/$defs/qdt:UnitMeasureUnitCodeContentType_4"
				}
			},
			"required": [
				"@unitCode"
			],
			"additionalProperties": false
		},
		"qdt:UnitMeasureType_5": {
			"description": "QDT\nUnit_ Measure. Type",
			"$ref": "#/$defs/qdt:decimal_3",
			"additionalProperties": false
		},
		"qdt:UnitMeasureType_6": {
			"description": "QDT\nUnit_ Measure. Type",
			"type": [
				"object"
			],
			"properties": {
				"$": {
					"$ref": "#/$defs/qdt:decimal_3"
				},
				"@unitCode": {
					"$ref": "#/$defs/qdt:UnitMeasureUnitCodeContentType_5"
				}
			},
			"required": [
				"@unitCode"
			],
			"additionalProperties": false
		},
		"qdt:UnitMeasureType_7": {
			"description": "QDT\nUnit_ Measure. Type",
			"type": [
				"object"
			],
			"properties": {
				"$": {
					"$ref": "#/$defs/qdt:decimal"
				},
				"@unitCode": {
					"$ref": "#/$defs/qdt:UnitMeasureUnitCodeContentType_6"
				}
			},
			"required": [
				"@unitCode"
			],
			"additionalProperties": false
		},
		"qdt:UnitMeasureUnitCodeContentType_2": {
			"type": "string",
			"minLength": 1,
			"maxLength": 4,
			"enum": [
				"GT"
			]
		},
		"qdt:UnitMeasureUnitCodeContentType_3": {
			"type": "string",
			"minLength": 1,
			"maxLength": 4,
			"enum": [
				"C24"
			]
		},
		"qdt:UnitMeasureUnitCodeContentType_4": {
			"type": "string",
			"minLength": 1,
			"maxLength": 4,
			"enum": [
				"CEL"
			]
		},
		"qdt:UnitMeasureUnitCodeContentType_5": {
			"type": "string",
			"minLength": 1,
			"maxLength": 4,
			"enum": [
				"2Q",
				"4N",
				"BQL",
				"GBQ"
			]
		},
		"qdt:UnitMeasureUnitCodeContentType_6": {
			"type": "string",
			"minLength": 1,
			"maxLength": 4,
			"enum": [
				"59"
			]
		},
		"qdt:VolumeUnitMeasureType_2": {
			"description": "QDT\nVolume_ Unit_ Measure. Type",
			"type": [
				"object"
			],
			"properties": {
				"$": {
					"$ref": "#/$defs/qdt:decimal"
				},
				"@unitCode": {
					"$ref": "#/$defs/qdt:VolumeUnitMeasureUnitCodeContentType_2"
				}
			},
			"required": [
				"@unitCode"
			],
			"additionalProperties": false
		},
		"qdt:VolumeUnitMeasureType_3": {
			"description": "QDT\nVolume_ Unit_ Measure. Type",
			"type": [
				"object"
			],
			"properties": {
				"$": {
					"$ref": "#/$defs/qdt:decimal"
				},
				"@unitCode": {
					"$ref": "#/$defs/qdt:VolumeUnitMeasureUnitCodeContentType"
				}
			},
			"required": [
				"@unitCode"
			],
			"additionalProperties": false
		},
		"qdt:VolumeUnitMeasureUnitCodeContentType": {
			"type": "string",
			"minLength": 1,
			"maxLength": 4,
			"enum": [
				"LTR",
				"MTQ"
			]
		},
		"qdt:VolumeUnitMeasureUnitCodeContentType_2": {
			"type": "string",
			"minLength": 1,
			"maxLength": 4,
			"enum": [
				"MTQ"
			]
		},
		"qdt:WeightUnitMeasureType_2": {
			"description": "QDT\nWeight_ Unit_ Measure. Type",
			"type": [
				"object"
			],
			"properties": {
				"$": {
					"$ref": "#/$defs/qdt:decimal"
				},
				"@unitCode": {
					"$ref": "#/$defs/qdt:WeightUnitMeasureUnitCodeContentType"
				}
			},
			"required": [
				"@unitCode"
			],
			"additionalProperties": false
		},
		"qdt:WeightUnitMeasureType_3": {
			"description": "QDT\nWeight_ Unit_ Measure. Type",
			"type": [
				"object"
			],
			"properties": {
				"$": {
					"$ref": "#/$defs/qdt:decimal_3"
				},
				"@unitCode": {
					"$ref": "#/$defs/qdt:WeightUnitMeasureUnitCodeContentType"
				}
			},
			"required": [
				"@unitCode"
			],
			"additionalProperties": false
		},
		"qdt:WeightUnitMeasureType_4": {
			"description": "QDT\nWeight_ Unit_ Measure. Type",
			"oneOf": [
				{
					"type": "object",
					"properties": {
						"$": {
							"$ref": "#/$defs/qdt:decimal"
						},
						"@unitCode": {
							"$ref": "#/$defs/qdt:WeightUnitMeasureUnitCodeContentType"
						}
					},
					"additionalProperties": false
				},
				{
					"$ref": "#/$defs/qdt:decimal"
				}
			]
		},
		"qdt:WeightUnitMeasureUnitCodeContentType": {
			"type": "string",
			"minLength": 1,
			"maxLength": 4,
			"enum": [
				"KGM",
				"TNE"
			]
		},
		"qdt:decimal": {
			"type": "number",
			"exclusiveMinimum": 0
		},
		"qdt:decimal_2": {
			"type": "number",
			"exclusiveMinimum": 0
		},
		"qdt:decimal_3": {
			"type": "number"
		},
		"qdt:decimal_4": {
			"type": "number"
		},
		"qdt:token": {
			"type": "string",
			"maxLength": 70
		},
		"ram:ApplicableFumigationType_2": {
			"description": "Application Fumigation\nABIE\nApplicable_ Fumigation. Details",
			"type": "object",
			"properties": {
				"ram:ExpertName": {
					"description": "DE-053-12 Fumigation expert name\nExpert Name Text",
					"$ref": "#/$defs/udt:TextType_6"
				},
				"ram:GasParticleMeasure": {
					"description": "DE-053-11 Fumigation gas particle measure\nGas Particle Measure",
					"$ref": "#/$defs/qdt:UnitMeasureType_7"
				},
				"ram:MethodDescription": {
					"description": "DE-053-06 Fumigation method description\nMethod Description Text",
					"$ref": "#/$defs/udt:TextType_4"
				},
				"ram:OccurrenceDate": {
					"description": "DE-053-04 Fumigation date\nOccurrence Date",
					"$ref": "#/$defs/qdt:FormattedDateType"
				},
				"ram:OccurrenceLocation": {
					"description": "DE-053-05 Fumigation place identification\nOccurrence Location Text",
					"$ref": "#/$defs/udt:TextType_5"
				},
				"ram:PrearrivalGasCheckCompletedIndicator": {
					"description": "DE-053-09 Fumigation gas check indicator\nPrearrival Gas Check Completed Indicator",
					"$ref": "#/$defs/udt:IndicatorType"
				},
				"ram:PrearrivalRemnantsRemovedIndicator": {
					"description": "DE-053-13 Fumigation remnants removed indicator\nPrearrival Remnants Removed Indicator",
					"$ref": "#/$defs/udt:IndicatorType"
				},
				"ram:UsedFumigantName": {
					"description": "DE-053-02 Fumigant name\nUsed Fumigant Name Text",
					"$ref": "#/$defs/udt:TextType_5"
				},
				"ram:VentilatedIndicator": {
					"description": "DE-053-07 Fumigation ventilated indicator\nVentilated Indicator",
					"$ref": "#/$defs/udt:IndicatorType"
				}
			},
			"additionalProperties": false
		},
		"ram:ApplicableTransshipmentType_2": {
			"description": "Applicable Transshipment\nABIE\nApplicable_ Transshipment. Details",
			"type": "object",
			"properties": {
				"ram:DangerousGoodsStorageLogisticsLocation": {
					"description": "Dangerous Goods Storage Location",
					"$ref": "#/$defs/ram:LogisticsLocationType_2"
				},
				"ram:OccurrenceDateTime": {
					"description": "DE-054-10 Transshipment date time\nOccurrence Date Time",
					"$ref": "#/$defs/qdt:FormattedDateTimeType"
				},
				"ram:UsedReferencedTransportMeans": {
					"description": "Used Transport Means",
					"$ref": "#/$defs/ram:ReferencedTransportMeansType_2"
				}
			},
			"additionalProperties": false
		},
		"ram:DocumentAuthenticationType_2": {
			"description": "Document Authentication\nABIE\nDocument_ Authentication. Details",
			"type": "object",
			"properties": {
				"ram:FormattedActualDateTime": {
					"description": "DE-002-02 Authentication date time\nActual Formatted Date Time",
					"$ref": "#/$defs/qdt:FormattedDateTimeType"
				}
			},
			"required": [
				"ram:FormattedActualDateTime"
			],
			"additionalProperties": false
		},
		"ram:ExchangedDeclarationType_2": {
			"description": "Exchanged Declaration\nABIE\nExchanged_ Declaration. Details",
			"type": "object",
			"properties": {
				"ram:StatementTypeCode": {
					"type": "array",
					"minItems": 1,
					"items": {
						"description": "DE-003-07 Declarant statement, coded\nStatement Type Code",
						"$ref": "#/$defs/qdt:StatementTypeCodeType_2"
					}
				}
			},
			"required": [
				"ram:StatementTypeCode"
			],
			"additionalProperties": false
		},
		"ram:ExchangedDeclarationType_3": {
			"description": "Exchanged Declaration\nABIE\nExchanged_ Declaration. Details",
			"type": "object",
			"properties": {
				"ram:CustomsAssignedID": {
					"description": "DE-002-13 MRN\nCustoms Assigned Identifier",
					"$ref": "#/$defs/udt:IDType_16"
				},
				"ram:DeclarantTradeParty": {
					"description": "Declarant",
					"$ref": "#/$defs/ram:TradePartyType_3"
				},
				"ram:ID": {
					"description": "DE-002-09 LRN\nID",
					"$ref": "#/$defs/udt:IDType_15"
				}
			},
			"required": [
				"ram:DeclarantTradeParty"
			],
			"additionalProperties": false
		},
		"ram:ExchangedDocumentType_2": {
			"description": "Exchanged Document\nABIE\nExchanged_ Document. Details",
			"type": "object",
			"properties": {
				"ram:AttachedSpecifiedBinaryFile": {
					"type": "array",
					"items": {
						"description": "Attached File",
						"$ref": "#/$defs/ram:SpecifiedBinaryFileType_2"
					}
				},
				"ram:Remarks": {
					"description": "DE-003-01 Remarks\nDE-014-08 Security, other matters to report\nRemark",
					"$ref": "#/$defs/udt:TextType_2"
				}
			},
			"additionalProperties": false
		},
		"ram:ExchangedDocumentType_3": {
			"description": "Exchanged Document\nABIE\nExchanged_ Document. Details",
			"type": "object",
			"properties": {
				"ram:FirstSignatoryDocumentAuthentication": {
					"description": "First Signatory Authentication",
					"$ref": "#/$defs/ram:DocumentAuthenticationType_2"
				},
				"ram:ID": {
					"description": "DE-002-07 Message identifier\nID",
					"$ref": "#/$defs/udt:IDType_13"
				},
				"ram:PurposeCode": {
					"description": "DE-002-08 Message function, coded\nPurpose Code",
					"$ref": "#/$defs/qdt:MessageFunctionCodeType_2"
				},
				"ram:TypeCode": {
					"description": "DE-002-03 Formality type, coded\nType Code",
					"$ref": "#/$defs/qdt:FormalityTypesCodeType_2"
				},
				"ram:VersionID": {
					"description": "DE-002-10 Version\nVersion ID",
					"$ref": "#/$defs/udt:IDType_14"
				}
			},
			"required": [
				"ram:FirstSignatoryDocumentAuthentication",
				"ram:ID",
				"ram:PurposeCode",
				"ram:TypeCode",
				"ram:VersionID"
			],
			"additionalProperties": false
		},
		"ram:HandlingInstructionsType_2": {
			"description": "Handling Instructions\nABIE\nHandling_ Instructions. Details",
			"type": "object",
			"properties": {
				"ram:OccurrenceLogisticsLocation": {
					"description": "Occurrence Location",
					"$ref": "#/$defs/ram:LogisticsLocationType_3"
				}
			},
			"required": [
				"ram:OccurrenceLogisticsLocation"
			],
			"additionalProperties": false
		},
		"ram:LogisticsLocationType_2": {
			"description": "Logistics Location\nABIE\nLogistics_ Location. Details",
			"type": "object",
			"properties": {
				"ram:Name": {
					"description": "DE-046-14 Dangerous goods transhipment location\nName",
					"$ref": "#/$defs/udt:TextType_6"
				}
			},
			"required": [
				"ram:Name"
			],
			"additionalProperties": false
		},
		"ram:LogisticsLocationType_3": {
			"description": "Logistics Location\nABIE\nLogistics_ Location. Details",
			"type": "object",
			"properties": {
				"ram:Name": {
					"description": "DE-047-49 Place of handling name\nName",
					"$ref": "#/$defs/udt:TextType_9"
				}
			},
			"required": [
				"ram:Name"
			],
			"additionalProperties": false
		},
		"ram:LogisticsLocationType_4": {
			"description": "Logistics Location\nABIE\nLogistics_ Location. Details",
			"type": "object",
			"properties": {
				"ram:ID": {
					"description": "DE-047-01 Port of loading, coded\nID",
					"$ref": "#/$defs/udt:IDType_8"
				}
			},
			"required": [
				"ram:ID"
			],
			"additionalProperties": false
		},
		"ram:LogisticsLocationType_5": {
			"description": "Logistics Location\nABIE\nLogistics_ Location. Details",
			"type": "object",
			"properties": {
				"ram:ID": {
					"description": "DE-047-04 Port of discharge, coded\nID",
					"$ref": "#/$defs/udt:IDType_8"
				}
			},
			"required": [
				"ram:ID"
			],
			"additionalProperties": false
		},
		"ram:LogisticsPackageType_2": {
			"description": "Logistics Package\nABIE\nLogistics_ Package. Details",
			"type": "object",
			"properties": {
				"ram:ItemQuantity": {
					"description": "DE-049-15 Dangerous goods number of packages\nItem Quantity",
					"$ref": "#/$defs/udt:QuantityType_3"
				},
				"ram:LevelCode": {
					"description": "DE-049-35 Dangerous goods packing level, coded\nLevel Code",
					"$ref": "#/$defs/qdt:PackagingLevelCodeType_2"
				},
				"ram:PhysicalLogisticsShippingMarks": {
					"description": "Shipping Marks",
					"$ref": "#/$defs/ram:LogisticsShippingMarksType_2"
				},
				"ram:TypeCode": {
					"description": "DE-049-16 Dangerous goods package type, coded\nType Code",
					"$ref": "#/$defs/qdt:PackageTypeCodeType_2"
				}
			},
			"required": [
				"ram:TypeCode"
			],
			"additionalProperties": false
		},
		"ram:LogisticsPackageType_3": {
			"description": "Logistics Package\nABIE\nLogistics_ Package. Details",
			"type": "object",
			"properties": {
				"ram:ItemQuantity": {
					"description": "DE-049-15 Dangerous goods number of packages\nItem Quantity",
					"$ref": "#/$defs/udt:QuantityType_4"
				},
				"ram:LevelCode": {
					"description": "DE-049-35 Dangerous goods packing level, coded\nLevel Code",
					"$ref": "#/$defs/qdt:PackagingLevelCodeType_2"
				},
				"ram:TypeCode": {
					"description": "DE-049-16 Dangerous goods package type, coded\nType Code",
					"$ref": "#/$defs/qdt:PackageTypeCodeType_2"
				}
			},
			"required": [
				"ram:TypeCode"
			],
			"additionalProperties": false
		},
		"ram:LogisticsPackageType_4": {
			"description": "Logistics Package\nABIE\nLogistics_ Package. Details",
			"type": "object",
			"properties": {
				"ram:PhysicalLogisticsShippingMarks": {
					"description": "Shipping Marks",
					"$ref": "#/$defs/ram:LogisticsShippingMarksType_3"
				}
			},
			"required": [
				"ram:PhysicalLogisticsShippingMarks"
			],
			"additionalProperties": false
		},
		"ram:LogisticsShippingMarksType_2": {
			"description": "Logistics Shipping Marks\nABIE\nLogistics_ Shipping Marks. Details",
			"type": "object",
			"properties": {
				"ram:MarkingInstructionCode": {
					"description": "DE-049-31 Cargo marking Instructions, coded\nMarking Instruction Code",
					"$ref": "#/$defs/qdt:MarkingInstructionCodeType_2"
				}
			},
			"required": [
				"ram:MarkingInstructionCode"
			],
			"additionalProperties": false
		},
		"ram:LogisticsShippingMarksType_3": {
			"description": "Logistics Shipping Marks\nABIE\nLogistics_ Shipping Marks. Details",
			"type": "object",
			"properties": {
				"ram:Marking": {
					"description": "DE-048-08 Cargo item marks and numbers\nMarking Text",
					"$ref": "#/$defs/udt:TextType_10"
				}
			},
			"required": [
				"ram:Marking"
			],
			"additionalProperties": false
		},
		"ram:LogisticsTransportEquipmentType_2": {
			"description": "Logistics Transport Equipment\nABIE\nLogistics_ Transport Equipment. Details",
			"type": "object",
			"properties": {
				"ram:AtmosphericPressureMeasure": {
					"description": "DE-052-04 Pressure measure\nAtmospheric Pressure Measure",
					"$ref": "#/$defs/udt:MeasureType_2"
				},
				"ram:CategoryCode": {
					"description": "DE-051-22 Transport equipment category, coded\nCategory Code",
					"$ref": "#/$defs/udt:CodeType_4"
				},
				"ram:CharacteristicCode": {
					"description": "DE-051-13 Transport equipment size and type, coded\nSize/Type Code",
					"$ref": "#/$defs/qdt:TransportEquipmentSizeTypeCodeType_2"
				},
				"ram:EmptyTankResidueDangerousGoods": {
					"description": "Empty Tank DG Residue",
					"$ref": "#/$defs/ram:ResidueDangerousGoodsType_2"
				},
				"ram:FumigatedIndicator": {
					"description": "DE-052-05 Fumigated indicator\nFumigated Indicator",
					"$ref": "#/$defs/udt:IndicatorType"
				},
				"ram:ID": {
					"description": "DE-051-01 Transport equipment identification number\nID",
					"$ref": "#/$defs/udt:IDType_11"
				},
				"ram:MaritimeContainerCharacteristicCode": {
					"description": "DE-051-17 Container size and type, coded\nMaritime Container Size/Type Code",
					"$ref": "#/$defs/udt:CodeType_6"
				},
				"ram:OperationalStatusCode": {
					"description": "DE-051-18 Transport equipment status, coded\nOperational Status Code",
					"$ref": "#/$defs/qdt:TransportEquipmentOperationalStatusCodeType_2"
				},
				"ram:OxygenContentPercent": {
					"description": "DE-052-03 Oxygen content percentage\nOxygen Content Percentage",
					"$ref": "#/$defs/udt:PercentType_2"
				},
				"ram:PreviousHoldCargoName": {
					"description": "DE-052-07 Previous goods in holds\nPrevious Hold Cargo Name Text",
					"$ref": "#/$defs/udt:TextType_4"
				},
				"ram:RelatedVentilationEvent": {
					"description": "Related Ventilation Event",
					"$ref": "#/$defs/ram:VentilationEventType_2"
				},
				"ram:SequenceNumeric": {
					"description": "DE-001-02 Sequence number\nSequence Number",
					"$ref": "#/$defs/udt:NumericType_2"
				},
				"ram:SpecifiedApplicableFumigation": {
					"description": "Applicable Fumigation",
					"$ref": "#/$defs/ram:ApplicableFumigationType_2"
				},
				"ram:StowagePositionID": {
					"description": "DE-051-02 Position on board\nStowage Position",
					"$ref": "#/$defs/udt:IDType_2"
				},
				"ram:TankStatusCode": {
					"description": "DE-052-01 Tank status, coded\nTank Status Code",
					"$ref": "#/$defs/qdt:TankStatusCodeType_2"
				},
				"ram:UsedCapacityCode": {
					"description": "DE-051-21 Transport equipment full or empty indicator, coded\nFull/Empty Code",
					"$ref": "#/$defs/udt:CodeType_5"
				},
				"ram:VentilatedIndicator": {
					"description": "DE-052-06 Cargo tanks ventilated indicator\nVentilation Indicator",
					"$ref": "#/$defs/udt:IndicatorType"
				}
			},
			"required": [
				"ram:CategoryCode",
				"ram:SequenceNumeric"
			],
			"additionalProperties": false
		},
		"ram:LogisticsTransportMeansType_2": {
			"description": "Logistics Transport Means\nABIE\nLogistics_ Transport Means. Details",
			"type": "object",
			"properties": {
				"ram:ConstructionSpecifiedTransportMeansCharacteristic": {
					"description": "Construction Characteristic",
					"$ref": "#/$defs/ram:SpecifiedTransportMeansCharacteristicType_2"
				},
				"ram:DGPeriodicAuthorizationReferencedDocument": {
					"description": "DG Periodic Authorization Document",
					"$ref": "#/$defs/ram:ReferencedDocumentType_2"
				},
				"ram:GasFreeCertificateIndicator": {
					"description": "DE-046-09 Gas free certificate indicator\nGas Free Certificate",
					"$ref": "#/$defs/udt:IndicatorType"
				},
				"ram:GasMeasuringEquipmentIndicator": {
					"description": "DE-053-08 Fumigant gas measuring equipment indicator\nGas Measuring Equipment Indicator",
					"$ref": "#/$defs/udt:IndicatorType"
				},
				"ram:INFID": {
					"description": "DE-046-01 INF ship class, coded\nINF ID",
					"$ref": "#/$defs/qdt:INFShipClassIDType_2"
				},
				"ram:RegulationComplianceIndicator": {
					"description": "DE-053-14 Fumigation regulations compliance indicator\nRegulation Compliance Indicator",
					"$ref": "#/$defs/udt:IndicatorType"
				}
			},
			"additionalProperties": false
		},
		"ram:LogisticsTransportMeansType_3": {
			"description": "Logistics Transport Means\nABIE\nLogistics_ Transport Means. Details",
			"type": "object",
			"properties": {
				"ram:LicencePlateID": {
					"description": "DE-065-04 Vehicle license plate number\nLicence Plate ID",
					"$ref": "#/$defs/udt:IDType_2"
				},
				"ram:VINID": {
					"description": "DE-065-05 Vehicle identification number (VIN)\nVIN ID",
					"$ref": "#/$defs/udt:IDType_12"
				}
			},
			"additionalProperties": false
		},
		"ram:LogisticsTransportMovementType_2": {
			"description": "Logistics Transport Movement\nABIE\nLogistics_ Transport Movement. Details",
			"type": "object",
			"properties": {
				"ram:BalticMOUIndicator": {
					"description": "DE-046-08 Baltic MOU indicator\nBaltic MOU Indicator",
					"$ref": "#/$defs/udt:IndicatorType"
				},
				"ram:CallTransportEvent": {
					"description": "Call Event",
					"$ref": "#/$defs/ram:TransportEventType_2"
				},
				"ram:CargoApplicableTransshipment": {
					"type": "array",
					"items": {
						"description": "Cargo Transshipment",
						"$ref": "#/$defs/ram:ApplicableTransshipmentType_2"
					}
				},
				"ram:DGManifestOnboardIndicator": {
					"description": "DE-046-02 DPG list on board indicator\nDG Manifest Onboard Indicator",
					"$ref": "#/$defs/udt:IndicatorType"
				},
				"ram:DangerousGoodsInformationTradeContact": {
					"description": "Dangerous Goods Contact Person",
					"$ref": "#/$defs/ram:TradeContactType_2"
				},
				"ram:UsedLogisticsTransportMeans": {
					"description": "Used Transport Means",
					"$ref": "#/$defs/ram:LogisticsTransportMeansType_2"
				}
			},
			"required": [
				"ram:DGManifestOnboardIndicator"
			],
			"additionalProperties": false
		},
		"ram:LogisticsTransportMovementType_3": {
			"description": "Logistics Transport Movement\nABIE\nLogistics_ Transport Movement. Details",
			"type": "object",
			"properties": {
				"ram:ModeCode": {
					"description": "DE-047-28 Next transport mode, coded\nMode Code",
					"$ref": "#/$defs/qdt:TransportModeCodeType_2"
				}
			},
			"required": [
				"ram:ModeCode"
			],
			"additionalProperties": false
		},
		"ram:LogisticsTransportMovementType_4": {
			"description": "Logistics Transport Movement\nABIE\nLogistics_ Transport Movement. Details",
			"type": "object",
			"properties": {
				"ram:CallTransportEvent": {
					"description": "Call Event",
					"$ref": "#/$defs/ram:TransportEventType_5"
				}
			},
			"required": [
				"ram:CallTransportEvent"
			],
			"additionalProperties": false
		},
		"ram:MeasurementType_2": {
			"description": "Measurement\nABIE\nMeasurement. Details",
			"type": "object",
			"properties": {
				"ram:ActualMeasure": {
					"description": "DE-049-09 Dangerous goods flashpoint\nActual Measure",
					"$ref": "#/$defs/qdt:UnitMeasureType_4"
				},
				"ram:TypeCode": {
					"description": "DE-049-34 Dangerous goods flashpoint description, coded\nType Code",
					"$ref": "#/$defs/qdt:FlashpointDescriptionCodeType_2"
				}
			},
			"required": [
				"ram:TypeCode"
			],
			"additionalProperties": false
		},
		"ram:MeasurementType_3": {
			"description": "Measurement\nABIE\nMeasurement. Details",
			"type": "object",
			"properties": {
				"ram:ActualMeasure": {
					"description": "DE-049-28 Control temperature\nActual Measure",
					"$ref": "#/$defs/qdt:UnitMeasureType_4"
				}
			},
			"required": [
				"ram:ActualMeasure"
			],
			"additionalProperties": false
		},
		"ram:MeasurementType_4": {
			"description": "Measurement\nABIE\nMeasurement. Details",
			"type": "object",
			"properties": {
				"ram:ActualMeasure": {
					"description": "DE-049-29 Emergency temperature\nActual Measure",
					"$ref": "#/$defs/qdt:UnitMeasureType_4"
				}
			},
			"required": [
				"ram:ActualMeasure"
			],
			"additionalProperties": false
		},
		"ram:RadioactiveMaterialType_2": {
			"description": "Radioactive Material\nABIE\nRadioactive_ Material. Details",
			"type": "object",
			"properties": {
				"ram:ApplicableSpecifiedRadioactiveIsotope": {
					"description": "Applicable Radioactive Isotope",
					"$ref": "#/$defs/ram:SpecifiedRadioactiveIsotopeType_2"
				},
				"ram:CriticalitySafetyIndexMeasure": {
					"description": "DE-049-27 Radioactive criticality safety index\nCriticality Safety Index Measure",
					"$ref": "#/$defs/qdt:UnitMeasureType_5"
				},
				"ram:RadionuclideName": {
					"description": "DE-049-23 Class 7 nuclide name\nRadionuclide Name",
					"$ref": "#/$defs/udt:TextType_5"
				},
				"ram:TransportIndexMeasure": {
					"description": "DE-049-26 Radioactive index of transport\nTransport Index Measure",
					"$ref": "#/$defs/qdt:UnitMeasureType_5"
				},
				"ram:TypeCode": {
					"description": "DE-049-25 Class 7 category, coded\nType Code",
					"$ref": "#/$defs/qdt:ClassCategoryCodeType_2"
				}
			},
			"additionalProperties": false
		},
		"ram:ReferencedDocumentType_2": {
			"description": "Referenced Document\nABIE\nReferenced_ Document. Details",
			"type": "object",
			"properties": {
				"ram:ID": {
					"description": "DE-046-10 Dangerous goods periodic authorisation number\nID",
					"$ref": "#/$defs/udt:IDType_2"
				},
				"ram:IssueDate": {
					"description": "DE-046-11 Dangerous goods periodic authorisation issue date\nIssue Date",
					"$ref": "#/$defs/qdt:FormattedDateType"
				},
				"ram:IssuerTradeParty": {
					"description": "Issuer",
					"$ref": "#/$defs/ram:TradePartyType_2"
				}
			},
			"required": [
				"ram:ID",
				"ram:IssueDate",
				"ram:IssuerTradeParty"
			],
			"additionalProperties": false
		},
		"ram:ReferencedLogisticsTransportEquipmentType_2": {
			"description": "Referenced Logistics Transport Equipment\nABIE\nReferenced_ Logistics_ Transport Equipment. Details",
			"type": "object",
			"properties": {
				"ram:CategoryCode": {
					"description": "DE-051-22 Transport equipment category, coded\nCategory Code",
					"$ref": "#/$defs/udt:CodeType_4"
				},
				"ram:ID": {
					"description": "DE-051-01 Transport equipment identification number\nID",
					"$ref": "#/$defs/udt:IDType_11"
				},
				"ram:InactiveSpecifiedLogisticsTransportMeans": {
					"description": "Inactive Vehicle identification",
					"$ref": "#/$defs/ram:LogisticsTransportMeansType_3"
				},
				"ram:LoadedTransportDangerousGoods": {
					"description": "Loaded Dangerous Goods",
					"$ref": "#/$defs/ram:TransportDangerousGoodsType_3"
				},
				"ram:SequenceNumeric": {
					"description": "DE-001-02 Sequence number\nSequence Number",
					"$ref": "#/$defs/udt:NumericType_2"
				},
				"ram:StowagePositionID": {
					"description": "DE-051-02 Position on board\nStowage Position",
					"$ref": "#/$defs/udt:IDType_2"
				}
			},
			"required": [
				"ram:CategoryCode",
				"ram:SequenceNumeric"
			],
			"additionalProperties": false
		},
		"ram:ReferencedTransportMeansType_2": {
			"description": "Referenced Transport Means\nABIE\nReferenced_ Transport Means. Details",
			"type": "object",
			"properties": {
				"ram:CallSignID": {
					"description": "DE-054-05 Transshipment ship call sign\nCall Sign ID",
					"$ref": "#/$defs/udt:IDType_5"
				},
				"ram:DeadweightTonnageMeasure": {
					"description": "DE-054-07 Transshipment ship gross tonnage\nGross Tonnage",
					"$ref": "#/$defs/qdt:UnitMeasureType_2"
				},
				"ram:IMOID": {
					"description": "DE-054-03 Transshipment ship IMO number\nIMO ID",
					"$ref": "#/$defs/udt:IDType_3"
				},
				"ram:MMSIID": {
					"description": "DE-054-04 Transshipment ship MMSI number\nMMSI ID",
					"$ref": "#/$defs/udt:IDType_4"
				},
				"ram:Name": {
					"description": "DE-054-02 Transshipment destination ship name\nName",
					"$ref": "#/$defs/udt:TextType_6"
				},
				"ram:RegistrationTradeCountry": {
					"description": "Flag Country",
					"$ref": "#/$defs/ram:TradeCountryType_2"
				}
			},
			"additionalProperties": false
		},
		"ram:ResidueDangerousGoodsType_2": {
			"description": "Residue Dangerous Goods\nABIE\nResidue_ Dangerous Goods. Details",
			"type": "object",
			"properties": {
				"ram:HazardClassificationID": {
					"description": "DE-050-03 Empty tank last cargo hazard class, coded\nHazard Classification ID",
					"$ref": "#/$defs/udt:IDType_10"
				},
				"ram:MaritimePollutantTypeCode": {
					"description": "DE-050-04 Empty tank last cargo marine pollutant type, coded\nMaritime Pollutant Type Code",
					"$ref": "#/$defs/udt:CodeType_4"
				},
				"ram:ProperShippingName": {
					"description": "DE-050-01 Empty tank last dangerous cargo name\nProper Shipping Name",
					"$ref": "#/$defs/udt:TextType_5"
				},
				"ram:RegulationCode": {
					"description": "DE-050-05 Empty tank last cargo dangerous goods regulation, coded\nRegulation Code",
					"$ref": "#/$defs/qdt:DangerousGoodsRegulationCodeType_3"
				},
				"ram:UNDGIdentificationCode": {
					"description": "DE-050-02 Empty tank last cargo UNDG number, coded\nUNDG ID",
					"$ref": "#/$defs/udt:CodeType_7"
				}
			},
			"additionalProperties": false
		},
		"ram:SpecifiedBinaryFileType_2": {
			"description": "Binary File\nABIE\nSpecified_ Binary File. Details",
			"type": "object",
			"properties": {
				"ram:Description": {
					"description": "DE-003-03 Attachment description\nDescription",
					"$ref": "#/$defs/udt:TextType_4"
				},
				"ram:FileName": {
					"description": "DE-003-05 Attachment file name\nName",
					"$ref": "#/$defs/udt:TextType_3"
				},
				"ram:MIMECode": {
					"description": "DE-003-06 Attachment MIME type\nMIME Code",
					"$ref": "#/$defs/qdt:MIMECodeType_2"
				},
				"ram:TypeCode": {
					"description": "DE-003-02 Attachment type, coded\nType Code",
					"$ref": "#/$defs/qdt:AttachmentTypeCodeType_2"
				}
			},
			"required": [
				"ram:TypeCode"
			],
			"additionalProperties": false
		},
		"ram:SpecifiedPeriodType_2": {
			"description": "Period\nABIE\nSpecified_ Period. Details",
			"type": "object",
			"properties": {
				"ram:FormattedEndDateTime": {
					"description": "DE-052-09 Ventilation after fumigation end date time\nFormatted End Date Time",
					"$ref": "#/$defs/qdt:FormattedDateTimeType"
				},
				"ram:FormattedStartDateTime": {
					"description": "DE-052-08 Ventilation after fumigation start date time\nFormatted Start Date Time",
					"$ref": "#/$defs/qdt:FormattedDateTimeType"
				}
			},
			"additionalProperties": false
		},
		"ram:SpecifiedRadioactiveIsotopeType_2": {
			"description": "Radionuclide\nABIE\nSpecified_ Radioactive Isotope. Details",
			"type": "object",
			"properties": {
				"ram:ActivityLevelMeasure": {
					"description": "DE-049-24 Class 7 maximum activity\nActivity Level Measure",
					"$ref": "#/$defs/qdt:UnitMeasureType_6"
				}
			},
			"required": [
				"ram:ActivityLevelMeasure"
			],
			"additionalProperties": false
		},
		"ram:SpecifiedTankType_2": {
			"description": "Specified Tank\nABIE\nSpecified_ Tank. Details",
			"type": "object",
			"properties": {
				"ram:TotalCapacityVolumeMeasure": {
					"description": "DE-009-15 Tanks total capacity\nTotal Capacity Volume Measure",
					"$ref": "#/$defs/qdt:VolumeUnitMeasureType_2"
				}
			},
			"required": [
				"ram:TotalCapacityVolumeMeasure"
			],
			"additionalProperties": false
		},
		"ram:SpecifiedTransportMeansCharacteristicType_2": {
			"description": "Transport Means Characteristic\nABIE\nSpecified_ Transport Means Characteristic. Details",
			"type": "object",
			"properties": {
				"ram:LargestTankVolumeMeasure": {
					"description": "DE-009-16 Largest tank capacity\nLargest Tank Volume Measure",
					"$ref": "#/$defs/qdt:VolumeUnitMeasureType_2"
				},
				"ram:OnboardSpecifiedTank": {
					"description": "Onboard Tank",
					"$ref": "#/$defs/ram:SpecifiedTankType_2"
				},
				"ram:TankQuantity": {
					"description": "DE-009-14 Number of tanks\nTank Quantity",
					"$ref": "#/$defs/udt:QuantityType_2"
				}
			},
			"additionalProperties": false
		},
		"ram:SupplyChainConsignmentItemType_2": {
			"description": "Supply Chain Consignment Item\nABIE\nSupply Chain_ Consignment Item. Details",
			"type": "object",
			"properties": {
				"ram:ApplicableTransportDangerousGoods": {
					"description": "Transport Dangerous Goods",
					"$ref": "#/$defs/ram:TransportDangerousGoodsType_2"
				},
				"ram:AssociatedReferencedLogisticsTransportEquipment": {
					"type": "array",
					"items": {
						"description": "Associated Referenced Transport Equipment",
						"$ref": "#/$defs/ram:ReferencedLogisticsTransportEquipmentType_2"
					}
				},
				"ram:SequenceNumeric": {
					"description": "DE-048-01 Cargo item number\nSequence Number",
					"$ref": "#/$defs/udt:NumericType_2"
				},
				"ram:TransportLogisticsPackage": {
					"description": "Transport Package",
					"$ref": "#/$defs/ram:LogisticsPackageType_4"
				}
			},
			"required": [
				"ram:ApplicableTransportDangerousGoods",
				"ram:SequenceNumeric"
			],
			"additionalProperties": false
		},
		"ram:SupplyChainConsignmentType_2": {
			"description": "Supply Chain Consignment\nABIE\nSupply Chain_ Consignment. Details",
			"type": "object",
			"properties": {
				"ram:ApplicableTransportDangerousGoods": {
					"description": "Dangerous Goods",
					"$ref": "#/$defs/ram:TransportDangerousGoodsType_4"
				},
				"ram:CargoOperationCode": {
					"description": "DE-047-42 Cargo operation, coded\nCargo Operation Code",
					"$ref": "#/$defs/qdt:CargoOperationCodeType_2"
				},
				"ram:ConsignorAssignedID": {
					"description": "DE-056-01 Dangerous goods shipper's reference number\nConsignor Assigned ID",
					"$ref": "#/$defs/udt:IDType_2"
				},
				"ram:HandlingInstructions": {
					"description": "Handling Instructions",
					"$ref": "#/$defs/ram:HandlingInstructionsType_2"
				},
				"ram:IncludedSupplyChainConsignmentItem": {
					"type": "array",
					"minItems": 1,
					"items": {
						"description": "Included Consignment Item",
						"$ref": "#/$defs/ram:SupplyChainConsignmentItemType_2"
					}
				},
				"ram:LoadingTransportEvent": {
					"description": "Loading Event",
					"$ref": "#/$defs/ram:TransportEventType_3"
				},
				"ram:OnCarriageLogisticsTransportMovement": {
					"description": "On-Carriage Transport Movement",
					"$ref": "#/$defs/ram:LogisticsTransportMovementType_3"
				},
				"ram:SequenceNumeric": {
					"description": "DE-001-02 Sequence number\nSequence Number",
					"$ref": "#/$defs/udt:NumericType_2"
				},
				"ram:UnloadingTransportEvent": {
					"description": "Unloading Event",
					"$ref": "#/$defs/ram:TransportEventType_4"
				}
			},
			"required": [
				"ram:IncludedSupplyChainConsignmentItem",
				"ram:SequenceNumeric"
			],
			"additionalProperties": false
		},
		"ram:TradeAddressType_2": {
			"description": "Trade Address\nABIE\nTrade_ Address. Details",
			"type": "object",
			"properties": {
				"ram:AdditionalStreetName": {
					"description": "DE-004-07 Declarant address street additional line\nAdditional Street Name",
					"$ref": "#/$defs/udt:TextType_6"
				},
				"ram:BuildingNumber": {
					"description": "DE-004-08 Declarant address number\nBuilding Number",
					"$ref": "#/$defs/udt:TextType_8"
				},
				"ram:CityName": {
					"description": "DE-004-13 Declarant address city\nCity Name",
					"$ref": "#/$defs/udt:TextType_11"
				},
				"ram:CountryID": {
					"description": "DE-004-11 Declarant address country\nCountry Code",
					"$ref": "#/$defs/qdt:CountryIDType_2"
				},
				"ram:CountrySubDivisionName": {
					"description": "DE-004-10 Declarant address sub-division\nCountry Sub-Division Name",
					"$ref": "#/$defs/udt:TextType_8"
				},
				"ram:PostOfficeBox": {
					"description": "DE-004-09 Declarant address P.O. box\nPost Office Box",
					"$ref": "#/$defs/udt:TextType_6"
				},
				"ram:PostcodeCode": {
					"description": "DE-004-12 Declarant address postal code\nPostcode",
					"$ref": "#/$defs/udt:CodeType_8"
				},
				"ram:StreetName": {
					"description": "DE-004-06 Declarant address street\nStreet Name",
					"$ref": "#/$defs/udt:TextType_6"
				}
			},
			"required": [
				"ram:CityName",
				"ram:CountryID",
				"ram:PostcodeCode"
			],
			"additionalProperties": false
		},
		"ram:TradeContactType_2": {
			"description": "Trade Contact\nABIE\nTrade_ Contact. Details",
			"type": "object",
			"properties": {
				"ram:EmailURIUniversalCommunication": {
					"description": "Email Address",
					"$ref": "#/$defs/ram:UniversalCommunicationType_3"
				},
				"ram:ID": {
					"description": "DE-046-07 DPG contact tax number\nID",
					"$ref": "#/$defs/udt:IDType_6"
				},
				"ram:PersonName": {
					"description": "DE-046-03 DPG contact name\nPerson Name",
					"$ref": "#/$defs/udt:TextType_7"
				},
				"ram:RelatedTradeLocation": {
					"description": "Related Location",
					"$ref": "#/$defs/ram:TradeLocationType_2"
				},
				"ram:TelephoneUniversalCommunication": {
					"description": "Telephone",
					"$ref": "#/$defs/ram:UniversalCommunicationType_2"
				}
			},
			"additionalProperties": false
		},
		"ram:TradeContactType_3": {
			"description": "Trade Contact\nABIE\nTrade_ Contact. Details",
			"type": "object",
			"properties": {
				"ram:EmailURIUniversalCommunication": {
					"description": "Email Address",
					"$ref": "#/$defs/ram:UniversalCommunicationType_5"
				},
				"ram:PersonName": {
					"description": "DE-004-14 Declarant, Contact person: Name\nPerson Name",
					"$ref": "#/$defs/udt:TextType_6"
				},
				"ram:TelephoneUniversalCommunication": {
					"description": "Telephone",
					"$ref": "#/$defs/ram:UniversalCommunicationType_4"
				}
			},
			"required": [
				"ram:EmailURIUniversalCommunication",
				"ram:PersonName",
				"ram:TelephoneUniversalCommunication"
			],
			"additionalProperties": false
		},
		"ram:TradeCountryType_2": {
			"description": "Trade Country\nABIE\nTrade_ Country. Details",
			"type": "object",
			"properties": {
				"ram:ID": {
					"description": "DE-054-06 Transshipment ship flag, coded\nCode",
					"$ref": "#/$defs/qdt:CountryIDType_2"
				}
			},
			"required": [
				"ram:ID"
			],
			"additionalProperties": false
		},
		"ram:TradeLocationType_2": {
			"description": "Trade Location\nABIE\nTrade_ Location. Details",
			"type": "object",
			"properties": {
				"ram:ID": {
					"description": "DE-046-06 DPG contact location, coded\nID",
					"$ref": "#/$defs/udt:IDType_8"
				}
			},
			"required": [
				"ram:ID"
			],
			"additionalProperties": false
		},
		"ram:TradePartyType_2": {
			"description": "Trade Party\nABIE\nTrade_ Party. Details",
			"type": "object",
			"properties": {
				"ram:Name": {
					"description": "DE-046-12 Dangerous goods periodic authorisation issuer name\nName",
					"$ref": "#/$defs/udt:TextType_5"
				}
			},
			"required": [
				"ram:Name"
			],
			"additionalProperties": false
		},
		"ram:TradePartyType_3": {
			"description": "Trade Party\nABIE\nTrade_ Party. Details",
			"type": "object",
			"properties": {
				"ram:DefinedTradeContact": {
					"type": "array",
					"maxItems": 9,
					"items": {
						"description": "Defined Contact Details",
						"$ref": "#/$defs/ram:TradeContactType_3"
					}
				},
				"ram:EmailURIUniversalCommunication": {
					"type": "array",
					"maxItems": 9,
					"items": {
						"description": "Email Address",
						"$ref": "#/$defs/ram:UniversalCommunicationType_7"
					}
				},
				"ram:ID": {
					"description": "DE-004-01 Declarant identification number\nID",
					"$ref": "#/$defs/udt:IDType_11"
				},
				"ram:Name": {
					"description": "DE-004-02 Declarant name\nName",
					"$ref": "#/$defs/udt:TextType_6"
				},
				"ram:PostalTradeAddress": {
					"description": "Postal Address",
					"$ref": "#/$defs/ram:TradeAddressType_2"
				},
				"ram:RoleCode": {
					"description": "DE-004-03 Declarant role, coded\nRole Code",
					"$ref": "#/$defs/qdt:PartyRoleCodeType_2"
				},
				"ram:TelephoneUniversalCommunication": {
					"type": "array",
					"maxItems": 9,
					"items": {
						"description": "Telephone",
						"$ref": "#/$defs/ram:UniversalCommunicationType_6"
					}
				}
			},
			"required": [
				"ram:ID",
				"ram:RoleCode"
			],
			"additionalProperties": false
		},
		"ram:TransportDangerousGoodsType_2": {
			"description": "Transport Dangerous Goods\nABIE\nTransport_ Dangerous Goods. Details",
			"type": "object",
			"properties": {
				"ram:AdditionalHazardClassificationID": {
					"type": "array",
					"maxItems": 5,
					"items": {
						"description": "DE-049-14 Dangerous goods subsidiary risks, coded\nAdditional Hazard Classification ID",
						"$ref": "#/$defs/udt:IDType_10"
					}
				},
				"ram:ControlTemperatureMeasurement": {
					"description": "Control Temperature",
					"$ref": "#/$defs/ram:MeasurementType_3"
				},
				"ram:CriticalViscosityTemperatureMeasure": {
					"description": "DE-049-36 Viscosity critical temperature\nCritical Viscosity Temperature Measure",
					"$ref": "#/$defs/qdt:TemperatureUnitMeasureType_3"
				},
				"ram:DischargeTemperatureMeasure": {
					"description": "DE-049-22 Liquid bulk discharge temperature\nDischarge Temperature Measure",
					"$ref": "#/$defs/qdt:TemperatureUnitMeasureType_2"
				},
				"ram:EMSID": {
					"type": "array",
					"maxItems": 5,
					"items": {
						"description": "DE-049-13 Dangerous goods EmS number\nEMS ID",
						"$ref": "#/$defs/udt:IDType_9"
					}
				},
				"ram:EmergencyTemperatureMeasurement": {
					"description": "Emergency Temperature",
					"$ref": "#/$defs/ram:MeasurementType_4"
				},
				"ram:ExplosiveCargoNetWeightMeasure": {
					"description": "DE-049-17 Net explosive mass\nExplosive Cargo Net Weight",
					"$ref": "#/$defs/qdt:WeightUnitMeasureType_3"
				},
				"ram:FlashpointTemperatureMeasurement": {
					"description": "Flashpoint Temperature",
					"$ref": "#/$defs/ram:MeasurementType_2"
				},
				"ram:GrossVolumeMeasure": {
					"description": "DE-049-12 Dangerous goods volume\nGross Volume",
					"$ref": "#/$defs/qdt:VolumeUnitMeasureType_3"
				},
				"ram:GrossWeightMeasure": {
					"description": "DE-049-11 Dangerous goods gross mass\nGross Weight",
					"$ref": "#/$defs/qdt:WeightUnitMeasureType_2"
				},
				"ram:HazardClassificationID": {
					"description": "DE-049-02 Dangerous goods hazard class, coded\nHazard Classification ID",
					"$ref": "#/$defs/udt:IDType_10"
				},
				"ram:HazardousInBulkIndicator": {
					"description": "DE-049-30 Bulk hazardous material indicator\nHazardous In Bulk Indicator",
					"$ref": "#/$defs/udt:IndicatorType"
				},
				"ram:IMDGSegregationGroupCode": {
					"description": "DE-049-33 Dangerous goods segregation group, coded\nIMDG Segregation Group Code",
					"$ref": "#/$defs/udt:CodeType_3"
				},
				"ram:LimitedQuantityIndicator": {
					"description": "DE-049-18 Limited quantities indicator\nLimited Quantity Indicator",
					"$ref": "#/$defs/udt:IndicatorType"
				},
				"ram:MaritimePollutantTypeCode": {
					"description": "DE-049-08 Dangerous goods marine pollution type, coded\nMaritime Pollutant Type Code",
					"$ref": "#/$defs/udt:CodeType_4"
				},
				"ram:MeltingPointTemperatureMeasure": {
					"description": "DE-049-21 Liquid bulk melting point\nMelting Point Temperature Measure",
					"$ref": "#/$defs/qdt:TemperatureUnitMeasureType_2"
				},
				"ram:NetWeightMeasure": {
					"description": "DE-049-10 Dangerous goods net mass\nNet Weight",
					"$ref": "#/$defs/qdt:WeightUnitMeasureType_2"
				},
				"ram:PackagingDangerLevelCode": {
					"description": "DE-049-06 Dangerous goods packing group\nPackaging Danger Level Code",
					"$ref": "#/$defs/qdt:IMDGDangerousGoodsPackingGroupCodeType_2"
				},
				"ram:ProperShippingName": {
					"description": "DE-049-04 Dangerous goods proper shipping name\nProper Shipping Name",
					"$ref": "#/$defs/udt:TextType_10"
				},
				"ram:RadioactiveMaterial": {
					"description": "Radioactive Material",
					"$ref": "#/$defs/ram:RadioactiveMaterialType_2"
				},
				"ram:RegulationCode": {
					"description": "DE-049-01 Dangerous goods regulation, coded\nRegulation Code",
					"$ref": "#/$defs/qdt:DangerousGoodsRegulationCodeType_2"
				},
				"ram:SmallVolumeIndicator": {
					"description": "DE-049-19 Excepted quantities indicator\nSmall Volume Indicator",
					"$ref": "#/$defs/udt:IndicatorType"
				},
				"ram:SpecifiedLogisticsPackage": {
					"type": "array",
					"maxItems": 2,
					"items": {
						"description": "Dangerous Goods Logistics Package",
						"$ref": "#/$defs/ram:LogisticsPackageType_2"
					}
				},
				"ram:SupplementaryInformation": {
					"description": "DE-049-07 Dangerous goods additional information\nSupplementary Information",
					"$ref": "#/$defs/udt:TextType_10"
				},
				"ram:TechnicalName": {
					"description": "DE-049-05 Dangerous goods technical specifications\nTechnical Name",
					"$ref": "#/$defs/udt:TextType_5"
				},
				"ram:UNDGIdentificationCode": {
					"description": "DE-049-03 Dangerous goods UNDG number, coded\nUNDG ID",
					"$ref": "#/$defs/udt:CodeType_2"
				},
				"ram:ViscosityMeasure": {
					"description": "DE-049-20 Liquid bulk viscosity\nViscosity Measure",
					"$ref": "#/$defs/qdt:UnitMeasureType_3"
				}
			},
			"required": [
				"ram:ProperShippingName",
				"ram:RegulationCode"
			],
			"additionalProperties": false
		},
		"ram:TransportDangerousGoodsType_3": {
			"description": "Transport Dangerous Goods\nABIE\nTransport_ Dangerous Goods. Details",
			"type": "object",
			"properties": {
				"ram:ExplosiveCargoNetWeightMeasure": {
					"description": "DE-049-17 Net explosive mass\nExplosive Cargo Net Weight",
					"$ref": "#/$defs/qdt:WeightUnitMeasureType_4"
				},
				"ram:GrossWeightMeasure": {
					"description": "DE-049-11 Dangerous goods gross mass\nGross Weight",
					"$ref": "#/$defs/qdt:WeightUnitMeasureType_4"
				},
				"ram:NetWeightMeasure": {
					"description": "DE-049-10 Dangerous goods net mass\nNet Weight",
					"$ref": "#/$defs/qdt:WeightUnitMeasureType_4"
				},
				"ram:SpecifiedLogisticsPackage": {
					"type": "array",
					"maxItems": 2,
					"items": {
						"description": "Dangerous Goods Logistics Package",
						"$ref": "#/$defs/ram:LogisticsPackageType_3"
					}
				}
			},
			"required": [
				"ram:GrossWeightMeasure"
			],
			"additionalProperties": false
		},
		"ram:TransportDangerousGoodsType_4": {
			"description": "Transport Dangerous Goods\nABIE\nTransport_ Dangerous Goods. Details",
			"type": "object",
			"properties": {
				"ram:TransportExpertTradeContact": {
					"description": "Transport Expert Contact",
					"$ref": "#/$defs/ram:TradeContactType_2"
				}
			},
			"required": [
				"ram:TransportExpertTradeContact"
			],
			"additionalProperties": false
		},
		"ram:TransportEventType_2": {
			"description": "Transport Event\nABIE\nTransport_ Event. Details",
			"type": "object",
			"properties": {
				"ram:ExplosiveIndicator": {
					"description": "DE-046-13 Explosives or fireworks indicator\nExplosive or Firework Indicator",
					"$ref": "#/$defs/udt:IndicatorType"
				}
			},
			"required": [
				"ram:ExplosiveIndicator"
			],
			"additionalProperties": false
		},
		"ram:TransportEventType_3": {
			"description": "Transport Event\nABIE\nTransport_ Event. Details",
			"type": "object",
			"properties": {
				"ram:OccurrenceLogisticsLocation": {
					"description": "Occurrence Location",
					"$ref": "#/$defs/ram:LogisticsLocationType_4"
				},
				"ram:ScheduledOccurrenceDate": {
					"description": "DE-047-13 Expected date of loading\nScheduled Occurrence Date",
					"$ref": "#/$defs/qdt:FormattedDateType"
				}
			},
			"required": [
				"ram:OccurrenceLogisticsLocation"
			],
			"additionalProperties": false
		},
		"ram:TransportEventType_4": {
			"description": "Transport Event\nABIE\nTransport_ Event. Details",
			"type": "object",
			"properties": {
				"ram:OccurrenceLogisticsLocation": {
					"description": "Occurrence Location",
					"$ref": "#/$defs/ram:LogisticsLocationType_5"
				}
			},
			"required": [
				"ram:OccurrenceLogisticsLocation"
			],
			"additionalProperties": false
		},
		"ram:TransportEventType_5": {
			"description": "Transport Event\nABIE\nTransport_ Event. Details",
			"type": "object",
			"properties": {
				"ram:ID": {
					"description": "DE-014-01 Visit ID\nID",
					"$ref": "#/$defs/udt:IDType_12"
				}
			},
			"required": [
				"ram:ID"
			],
			"additionalProperties": false
		},
		"ram:UniversalCommunicationType_2": {
			"description": "Communication\nABIE\nUniversal_ Communication. Details",
			"type": "object",
			"properties": {
				"ram:CompleteNumber": {
					"description": "DE-046-04 DPG contact phone number\nComplete Number",
					"$ref": "#/$defs/udt:TextType_8"
				}
			},
			"required": [
				"ram:CompleteNumber"
			],
			"additionalProperties": false
		},
		"ram:UniversalCommunicationType_3": {
			"description": "Communication\nABIE\nUniversal_ Communication. Details",
			"type": "object",
			"properties": {
				"ram:URIID": {
					"description": "DE-046-05 DPG contact email\nURI",
					"$ref": "#/$defs/udt:IDType_7"
				}
			},
			"required": [
				"ram:URIID"
			],
			"additionalProperties": false
		},
		"ram:UniversalCommunicationType_4": {
			"description": "Communication\nABIE\nUniversal_ Communication. Details",
			"type": "object",
			"properties": {
				"ram:CompleteNumber": {
					"description": "DE-004-15 Declarant, Contact person: Phone number\nComplete Number",
					"$ref": "#/$defs/udt:TextType_8"
				}
			},
			"required": [
				"ram:CompleteNumber"
			],
			"additionalProperties": false
		},
		"ram:UniversalCommunicationType_5": {
			"description": "Communication\nABIE\nUniversal_ Communication. Details",
			"type": "object",
			"properties": {
				"ram:URIID": {
					"description": "DE-004-16 Declarant, Contact person: E-mail address\nURI",
					"$ref": "#/$defs/udt:IDType_7"
				}
			},
			"required": [
				"ram:URIID"
			],
			"additionalProperties": false
		},
		"ram:UniversalCommunicationType_6": {
			"description": "Communication\nABIE\nUniversal_ Communication. Details",
			"type": "object",
			"properties": {
				"ram:CompleteNumber": {
					"description": "DE-004-04 Declarant phone number\nComplete Number",
					"$ref": "#/$defs/udt:TextType_8"
				}
			},
			"required": [
				"ram:CompleteNumber"
			],
			"additionalProperties": false
		},
		"ram:UniversalCommunicationType_7": {
			"description": "Communication\nABIE\nUniversal_ Communication. Details",
			"type": "object",
			"properties": {
				"ram:URIID": {
					"description": "DE-004-05 Declarant e-mail address\nURI",
					"$ref": "#/$defs/udt:IDType_7"
				}
			},
			"required": [
				"ram:URIID"
			],
			"additionalProperties": false
		},
		"ram:VentilationEventType_2": {
			"description": "Fumigation\nABIE\nVentilation_ Event. Details",
			"type": "object",
			"properties": {
				"ram:MethodDescription": {
					"description": "DE-052-10 Ventilation method description\nDescription",
					"$ref": "#/$defs/udt:TextType_4"
				},
				"ram:OccurrenceSpecifiedPeriod": {
					"description": "Occurrence Period",
					"$ref": "#/$defs/ram:SpecifiedPeriodType_2"
				}
			},
			"additionalProperties": false
		},
		"udt:CodeType_2": {
			"description": "UDT\nCode. Type",
			"$ref": "#/$defs/udt:token",
			"additionalProperties": false
		},
		"udt:CodeType_3": {
			"description": "UDT\nCode. Type",
			"$ref": "#/$defs/udt:token_2",
			"additionalProperties": false
		},
		"udt:CodeType_4": {
			"description": "UDT\nCode. Type",
			"$ref": "#/$defs/udt:token_3",
			"additionalProperties": false
		},
		"udt:CodeType_5": {
			"description": "UDT\nCode. Type",
			"$ref": "#/$defs/udt:token_4",
			"additionalProperties": false
		},
		"udt:CodeType_6": {
			"description": "UDT\nCode. Type",
			"$ref": "#/$defs/udt:token_6",
			"additionalProperties": false
		},
		"udt:CodeType_7": {
			"description": "UDT\nCode. Type",
			"$ref": "#/$defs/udt:token_7",
			"additionalProperties": false
		},
		"udt:CodeType_8": {
			"description": "UDT\nCode. Type",
			"$ref": "#/$defs/udt:token_8",
			"additionalProperties": false
		},
		"udt:IDType_10": {
			"description": "UDT\nIdentifier. Type",
			"type": "string",
			"maxLength": 7
		},
		"udt:IDType_11": {
			"description": "UDT\nIdentifier. Type",
			"type": "string",
			"maxLength": 17
		},
		"udt:IDType_12": {
			"description": "UDT\nIdentifier. Type",
			"type": "string",
			"maxLength": 35
		},
		"udt:IDType_13": {
			"description": "UDT\nIdentifier. Type",
			"type": "string",
			"maxLength": 70
		},
		"udt:IDType_14": {
			"description": "UDT\nIdentifier. Type",
			"type": "string",
			"minLength": 1,
			"maxLength": 17
		},
		"udt:IDType_15": {
			"description": "UDT\nIdentifier. Type",
			"type": "string",
			"minLength": 1,
			"maxLength": 22
		},
		"udt:IDType_16": {
			"description": "UDT\nIdentifier. Type",
			"type": "string",
			"minLength": 18,
			"maxLength": 18
		},
		"udt:IDType_2": {
			"description": "UDT\nIdentifier. Type",
			"type": "string",
			"minLength": 1,
			"maxLength": 35
		},
		"udt:IDType_3": {
			"description": "UDT\nIdentifier. Type",
			"type": "string",
			"minLength": 7,
			"maxLength": 7,
			"pattern": "^\\d{7}$"
		},
		"udt:IDType_4": {
			"description": "UDT\nIdentifier. Type",
			"type": "string",
			"minLength": 9,
			"maxLength": 9,
			"pattern": "^\\d{9}$"
		},
		"udt:IDType_5": {
			"description": "UDT\nIdentifier. Type",
			"type": "string",
			"minLength": 1,
			"maxLength": 7
		},
		"udt:IDType_6": {
			"description": "UDT\nIdentifier. Type",
			"type": "string",
			"minLength": 1,
			"maxLength": 18
		},
		"udt:IDType_7": {
			"description": "UDT\nIdentifier. Type",
			"type": "string",
			"minLength": 1,
			"maxLength": 256
		},
		"udt:IDType_8": {
			"description": "UDT\nIdentifier. Type",
			"type": "string",
			"minLength": 5,
			"maxLength": 5
		},
		"udt:IDType_9": {
			"description": "UDT\nIdentifier. Type",
			"type": "string",
			"minLength": 1,
			"maxLength": 6
		},
		"udt:IndicatorType": {
			"description": "UDT Indicator. Type",
			"type": "integer",
			"minimum": 0,
			"enum": [
				0,
				1
			]
		},
		"udt:MeasureType_2": {
			"description": "UDT\nMeasure. Type",
			"type": [
				"object"
			],
			"properties": {
				"$": {
					"$ref": "#/$defs/udt:decimal"
				},
				"@unitCode": {
					"$ref": "#/$defs/udt:token_5"
				}
			},
			"required": [
				"@unitCode"
			],
			"additionalProperties": false
		},
		"udt:NumericType_2": {
			"description": "UDT\nNumeric. Type",
			"type": "integer",
			"exclusiveMinimum": 0
		},
		"udt:PercentType_2": {
			"description": "UDT\nPercent. Type",
			"type": "number"
		},
		"udt:QuantityType_2": {
			"description": "UDT\nQuantity. Type",
			"$ref": "#/$defs/udt:integer",
			"additionalProperties": false
		},
		"udt:QuantityType_3": {
			"description": "UDT\nQuantity. Type",
			"$ref": "#/$defs/udt:integer_2",
			"additionalProperties": false
		},
		"udt:QuantityType_4": {
			"description": "UDT\nQuantity. Type",
			"oneOf": [
				{
					"type": "object",
					"properties": {
						"$": {
							"$ref": "#/$defs/udt:integer_2"
						},
						"@unitCode": {
							"type": "string"
						}
					},
					"additionalProperties": false
				},
				{
					"$ref": "#/$defs/udt:integer_2"
				}
			]
		},
		"udt:TextType_10": {
			"description": "UDT\nText. Type",
			"$ref": "#/$defs/udt:string",
			"additionalProperties": false
		},
		"udt:TextType_11": {
			"description": "UDT\nText. Type",
			"oneOf": [
				{
					"type": "object",
					"properties": {
						"$": {
							"$ref": "#/$defs/udt:string_6"
						},
						"@languageID": {
							"type": "string"
						}
					},
					"additionalProperties": false
				},
				{
					"$ref": "#/$defs/udt:string_6"
				}
			]
		},
		"udt:TextType_2": {
			"description": "UDT\nText. Type",
			"oneOf": [
				{
					"type": "object",
					"properties": {
						"$": {
							"$ref": "#/$defs/udt:string"
						},
						"@languageID": {
							"type": "string"
						}
					},
					"additionalProperties": false
				},
				{
					"$ref": "#/$defs/udt:string"
				}
			]
		},
		"udt:TextType_3": {
			"description": "UDT\nText. Type",
			"$ref": "#/$defs/udt:string_2",
			"additionalProperties": false
		},
		"udt:TextType_4": {
			"description": "UDT\nText. Type",
			"oneOf": [
				{
					"type": "object",
					"properties": {
						"$": {
							"$ref": "#/$defs/udt:string_3"
						},
						"@languageID": {
							"type": "string"
						}
					},
					"additionalProperties": false
				},
				{
					"$ref": "#/$defs/udt:string_3"
				}
			]
		},
		"udt:TextType_5": {
			"description": "UDT\nText. Type",
			"$ref": "#/$defs/udt:string_3",
			"additionalProperties": false
		},
		"udt:TextType_6": {
			"description": "UDT\nText. Type",
			"$ref": "#/$defs/udt:string_4",
			"additionalProperties": false
		},
		"udt:TextType_7": {
			"description": "UDT\nText. Type",
			"$ref": "#/$defs/udt:string_5",
			"additionalProperties": false
		},
		"udt:TextType_8": {
			"description": "UDT\nText. Type",
			"$ref": "#/$defs/udt:string_6",
			"additionalProperties": false
		},
		"udt:TextType_9": {
			"description": "UDT\nText. Type",
			"oneOf": [
				{
					"type": "object",
					"properties": {
						"$": {
							"$ref": "#/$defs/udt:string_4"
						},
						"@languageID": {
							"type": "string"
						}
					},
					"additionalProperties": false
				},
				{
					"$ref": "#/$defs/udt:string_4"
				}
			]
		},
		"udt:decimal": {
			"type": "number",
			"exclusiveMinimum": 0
		},
		"udt:integer": {
			"type": "integer"
		},
		"udt:integer_2": {
			"type": "integer"
		},
		"udt:string": {
			"type": "string",
			"minLength": 1,
			"maxLength": 512
		},
		"udt:string_2": {
			"type": "string",
			"maxLength": 256
		},
		"udt:string_3": {
			"type": "string",
			"minLength": 1,
			"maxLength": 256
		},
		"udt:string_4": {
			"type": "string",
			"minLength": 1,
			"maxLength": 70
		},
		"udt:string_5": {
			"type": "string",
			"minLength": 1,
			"maxLength": 50
		},
		"udt:string_6": {
			"type": "string",
			"minLength": 1,
			"maxLength": 35
		},
		"udt:token": {
			"type": "string",
			"minLength": 4,
			"maxLength": 4
		},
		"udt:token_2": {
			"type": "string",
			"maxLength": 17
		},
		"udt:token_3": {
			"type": "string",
			"maxLength": 3
		},
		"udt:token_4": {
			"type": "string",
			"maxLength": 3,
			"enum": [
				"4",
				"5"
			]
		},
		"udt:token_5": {
			"type": "string",
			"enum": [
				"HN"
			]
		},
		"udt:token_6": {
			"type": "string",
			"maxLength": 4
		},
		"udt:token_7": {
			"type": "string",
			"minLength": 4,
			"maxLength": 4,
			"pattern": "^\\d{4}$"
		},
		"udt:token_8": {
			"type": "string",
			"minLength": 1,
			"maxLength": 17
		}
	}
}